{"stat.useItem.minecraft.quartz_block":2,"stat.pickup.minecraft.wooden_slab":1,"stat.leaveGame":327,"stat.drop.minecraft.gunpowder":1,"stat.drop.minecraft.redstone":512,"stat.useItem.minecraft.glowstone":378,"stat.mineBlock.minecraft.web":2,"stat.useItem.minecraft.diamond_hoe":2,"stat.useItem.minecraft.sandstone_stairs":128,"stat.pickup.minecraft.bucket":9,"stat.useItem.minecraft.rail":129,"stat.mineBlock.minecraft.wooden_slab":1,"stat.useItem.minecraft.anvil":15,"stat.pickup.minecraft.brown_mushroom":66,"stat.killEntity.Villager":1,"stat.drop.minecraft.gold_ingot":1,"stat.useItem.minecraft.iron_pickaxe":49,"stat.pickup.minecraft.stained_hardened_clay":1,"stat.craftItem.minecraft.wooden_pickaxe":5,"stat.pickup.minecraft.double_plant":2,"stat.drop.minecraft.diamond_chestplate":3,"stat.furnaceInteraction":24,"stat.useItem.minecraft.command_block_minecart":1,"stat.drop.minecraft.red_flower":1,"stat.craftItem.minecraft.leather_helmet":1,"stat.useItem.minecraft.double_plant":203,"stat.pickup.minecraft.beef":2,"stat.useItem.minecraft.trapdoor":22,"stat.useItem.minecraft.stained_glass":41,"stat.useItem.minecraft.fence":316,"stat.useItem.minecraft.dark_oak_door":1,"stat.useItem.minecraft.ice":3,"stat.useItem.minecraft.cauldron":4,"stat.useItem.minecraft.flint_and_steel":22,"stat.useItem.minecraft.wheat_seeds":94,"stat.pickup.minecraft.emerald":35,"stat.useItem.minecraft.dye":817,"stat.pickup.minecraft.lever":12,"stat.deaths":30,"stat.pickup.minecraft.egg":10,"stat.craftItem.minecraft.iron_pickaxe":1,"stat.pickup.minecraft.glass_pane":2,"stat.pickup.minecraft.item_frame":17,"stat.drop.minecraft.iron_ingot":1,"stat.useItem.minecraft.jukebox":4,"stat.mineBlock.minecraft.tallgrass":1,"stat.chestOpened":247,"stat.useItem.minecraft.lapis_ore":13,"stat.useItem.minecraft.stone":4829,"stat.useItem.minecraft.jungle_fence":33,"stat.pickup.minecraft.arrow":3,"stat.pickup.minecraft.lapis_ore":1,"stat.crouchOneCm":108646,"stat.pickup.minecraft.rail":1,"stat.craftItem.minecraft.iron_ingot":3,"stat.craftingTableInteraction":53,"stat.useItem.minecraft.emerald_ore":6,"stat.drop.minecraft.double_plant":1,"stat.useItem.minecraft.dark_oak_fence":19,"stat.drop.minecraft.rabbit":1,"stat.pickup.minecraft.dye":28,"stat.pickup.minecraft.wheat_seeds":77,"stat.useItem.minecraft.enchanting_table":5,"stat.pickup.minecraft.ice":1,"stat.mineBlock.minecraft.dirt":30,"stat.flowerPotted":2,"stat.drop.minecraft.porkchop":3,"stat.useItem.minecraft.cobblestone":642,"stat.useItem.minecraft.gravel":108,"stat.minecartOneCm":1036,"stat.useItem.minecraft.jungle_fence_gate":10,"stat.drop.minecraft.glass_pane":2,"stat.useItem.minecraft.yellow_flower":82,"stat.drop.minecraft.sapling":251,"stat.useItem.minecraft.tallgrass":96,"stat.pickup.minecraft.apple":7,"stat.pickup.minecraft.banner":7,"stat.useItem.minecraft.glass_pane":184,"stat.drop.minecraft.fish":6,"stat.craftItem.minecraft.planks":32,"stat.useItem.minecraft.barrier":8,"stat.craftItem.minecraft.dirt":1,"stat.useItem.minecraft.stonebrick":565,"stat.mineBlock.minecraft.log":10,"stat.useItem.minecraft.wooden_door":1,"stat.useItem.minecraft.grass_path":10,"stat.useItem.minecraft.spruce_door":2,"stat.pickup.minecraft.red_flower":25,"stat.pickup.minecraft.wool":61,"stat.drop.minecraft.grass":1,"stat.useItem.minecraft.iron_axe":6,"stat.drop.minecraft.stone_shovel":1,"stat.mineBlock.minecraft.cobblestone":123,"stat.useItem.minecraft.beacon":4,"stat.mineBlock.minecraft.yellow_flower":1,"stat.useItem.minecraft.skull":1,"stat.craftItem.minecraft.wool":1,"stat.drop.minecraft.saddle":3,"stat.useItem.minecraft.concrete_powder":4,"stat.drop.minecraft.cobblestone":1,"stat.useItem.minecraft.obsidian":119,"stat.useItem.minecraft.mob_spawner":7,"stat.craftItem.minecraft.furnace":1,"stat.pickup.minecraft.map":1024,"stat.pickup.minecraft.coal_ore":1,"stat.useItem.minecraft.spruce_fence_gate":38,"stat.flyOneCm":61807227,"stat.pickup.minecraft.fish":6,"stat.timeSinceDeath":239231,"stat.cauldronFilled":2,"stat.useItem.minecraft.wooden_slab":1294,"stat.useItem.minecraft.potato":1,"stat.mineBlock.minecraft.coal_ore":22,"stat.drop.minecraft.wool":89,"stat.useItem.minecraft.armor_stand":1,"stat.killEntity.Creeper":1,"stat.talkedToVillager":35,"stat.drop.minecraft.spawn_egg":634,"stat.pickup.minecraft.string":4,"stat.useItem.minecraft.milk_bucket":1,"stat.killEntity.Squid":8,"stat.sprintOneCm":7270396,"stat.useItem.minecraft.diamond_block":114,"stat.pickup.minecraft.bone_block":2,"stat.mineBlock.minecraft.diamond_ore":2,"stat.drop.minecraft.cauldron":32,"stat.pickup.minecraft.spawn_egg":133,"stat.craftItem.minecraft.leather_chestplate":1,"stat.useItem.minecraft.banner":25,"stat.useItem.minecraft.ladder":20,"stat.useItem.minecraft.diamond_ore":11,"stat.pickup.minecraft.iron_block":1,"stat.pickup.minecraft.snowball":1,"stat.useItem.minecraft.birch_stairs":79,"stat.diveOneCm":84458,"stat.pickup.minecraft.wheat":14,"stat.pickup.minecraft.sign":5,"stat.drop.minecraft.golden_shovel":1,"stat.pickup.minecraft.stained_glass_pane":8,"stat.drop.minecraft.apple":3,"stat.jump":61449,"stat.useItem.minecraft.sand":229,"stat.pickup.minecraft.coal":17,"stat.pickup.minecraft.iron_ingot":1,"stat.drop.minecraft.diamond_sword":2,"stat.pickup.minecraft.gunpowder":2,"stat.useItem.minecraft.coal_ore":65,"stat.pickup.minecraft.dirt":32,"stat.drop.minecraft.iron_shovel":1,"stat.useItem.minecraft.glass":158,"stat.useItem.minecraft.dispenser":5,"stat.useItem.minecraft.sapling":268,"stat.damageTaken":6547,"stat.useItem.minecraft.stone_brick_stairs":179,"stat.mineBlock.minecraft.red_flower":3,"stat.useItem.minecraft.gold_block":18,"stat.useItem.minecraft.carrot_on_a_stick":13,"stat.mineBlock.minecraft.sapling":2,"stat.noteblockTuned":1,"stat.useItem.minecraft.purple_shulker_box":4,"stat.useItem.minecraft.birch_fence":25,"stat.killEntity.Shulker":1,"stat.pickup.minecraft.potato":3,"stat.pickup.minecraft.shulker_shell":1,"stat.useItem.minecraft.chest":103,"stat.drop.minecraft.item_frame":12,"stat.useItem.minecraft.lava_bucket":8,"stat.useItem.minecraft.gold_ore":5,"stat.craftItem.minecraft.spectral_arrow":2,"stat.useItem.minecraft.item_frame":138,"stat.shulkerBoxOpened":3,"stat.pickup.minecraft.baked_potato":8,"stat.useItem.minecraft.stained_hardened_clay":934,"stat.useItem.minecraft.redstone_ore":23,"stat.useItem.minecraft.concrete":17,"stat.useItem.minecraft.netherrack":29,"stat.mobKills":104,"stat.useItem.minecraft.mossy_cobblestone":12,"stat.useItem.minecraft.cobblestone_wall":37,"stat.pickup.minecraft.diamond":2,"stat.pickup.minecraft.beetroot_seeds":2,"stat.pickup.minecraft.torch":33,"stat.drop.minecraft.diamond_shovel":1,"stat.drop.minecraft.mutton":1,"stat.useItem.minecraft.bookshelf":112,"stat.useItem.minecraft.planks":1816,"stat.useItem.minecraft.golden_shovel":1,"stat.pickup.minecraft.glowstone_dust":4,"stat.pickup.minecraft.porkchop":177,"stat.pickup.minecraft.glass":1,"stat.useItem.minecraft.water_bucket":654,"stat.drop.minecraft.map":1024,"stat.aviateOneCm":6084,"stat.craftItem.minecraft.stone_sword":1,"stat.craftItem.minecraft.blaze_powder":2,"stat.useItem.minecraft.fence_gate":31,"stat.hopperInspected":11,"stat.drop.minecraft.diamond":32,"stat.useItem.minecraft.spawn_egg":392,"stat.useItem.minecraft.oak_stairs":85,"stat.useItem.minecraft.dark_oak_stairs":13,"stat.pickup.minecraft.wooden_button":3,"stat.pickup.minecraft.filled_map":7,"stat.useItem.minecraft.minecart":14,"stat.pickup.minecraft.furnace":1,"stat.drop.minecraft.stained_hardened_clay":65,"stat.drop.minecraft.diamond_helmet":3,"stat.pickup.minecraft.end_rod":1,"stat.useItem.minecraft.stone_stairs":242,"stat.pickup.minecraft.skull":1,"stat.useItem.minecraft.hopper":26,"stat.drop.minecraft.snowball":1,"stat.pickup.minecraft.saddle":3,"stat.playOneMinute":11818044,"stat.drop.minecraft.chest":128,"stat.mineBlock.minecraft.ice":3,"stat.useItem.minecraft.quartz_ore":4,"stat.fallOneCm":95296,"stat.drop.minecraft.stone":566,"stat.drop.minecraft.dye":4,"stat.pickup.minecraft.red_mushroom":36,"stat.useItem.minecraft.iron_hoe":1,"stat.drop.minecraft.leaves2":64,"stat.pickup.minecraft.emerald_ore":1,"stat.useItem.minecraft.golden_rail":5,"stat.pickup.minecraft.feather":1,"stat.drop.minecraft.bone":1,"stat.useItem.minecraft.furnace":40,"stat.useItem.minecraft.stone_pickaxe":130,"stat.useItem.minecraft.stone_sword":2,"stat.useItem.minecraft.wool":249,"stat.useItem.minecraft.iron_bars":27,"stat.useItem.minecraft.torch":126,"stat.drop.minecraft.diamond_horse_armor":1,"stat.useItem.minecraft.log":973,"stat.useItem.minecraft.comparator":6,"stat.drop.minecraft.tallgrass":8,"stat.pickup.minecraft.log":26,"stat.pickup.minecraft.tallgrass":8,"stat.drop.minecraft.planks":1,"stat.pickup.minecraft.sapling":150,"stat.pickup.minecraft.beetroot":1,"stat.useItem.minecraft.wooden_pressure_plate":4,"stat.useItem.minecraft.stone_hoe":1,"stat.useItem.minecraft.beetroot_seeds":1,"stat.sneakTime":118817,"stat.pickup.minecraft.rabbit":1,"stat.drop.minecraft.bucket":15,"stat.useItem.minecraft.baked_potato":4,"stat.drop.minecraft.yellow_flower":1,"stat.useItem.minecraft.brewing_stand":4,"stat.pickup.minecraft.yellow_flower":16,"stat.pickup.minecraft.chest":1,"stat.craftItem.minecraft.leather_leggings":1,"stat.useItem.minecraft.lapis_block":12,"stat.pickup.minecraft.bone":2,"stat.pickup.minecraft.stone_pressure_plate":8,"stat.useItem.minecraft.repeater":2,"stat.useItem.minecraft.log2":177,"stat.drop.minecraft.glowstone_dust":4,"stat.drop.minecraft.leather_helmet":1,"stat.useItem.minecraft.diamond_sword":215,"stat.swimOneCm":53435,"stat.climbOneCm":48590,"stat.useItem.minecraft.end_rod":52,"stat.drop.minecraft.brown_mushroom":65,"stat.useItem.minecraft.dirt":8932,"stat.useItem.minecraft.red_flower":198,"stat.useItem.minecraft.iron_ore":12,"stat.craftItem.minecraft.melon_block":1,"stat.craftItem.minecraft.stone_pickaxe":2,"stat.pickup.minecraft.cobblestone":134,"stat.drop.minecraft.fence":1,"stat.useItem.minecraft.stone_shovel":92,"stat.pickup.minecraft.redstone":7,"stat.mineBlock.minecraft.iron_ore":7,"stat.useItem.minecraft.sign":24,"stat.pickup.minecraft.mutton":4,"stat.useItem.minecraft.noteblock":2,"stat.drop.minecraft.coal":1,"stat.useItem.minecraft.lever":23,"stat.drop.minecraft.dirt":2,"stat.pickup.minecraft.carpet":9,"stat.useItem.minecraft.acacia_stairs":20,"stat.useItem.minecraft.sea_lantern":16,"stat.useItem.minecraft.spruce_fence":39,"stat.craftItem.minecraft.stick":32,"stat.useItem.minecraft.stone_slab":121,"stat.useItem.minecraft.bed":17,"stat.pickup.minecraft.grass":17,"stat.useItem.minecraft.stone_pressure_plate":151,"stat.drop.minecraft.leaves":96,"stat.useItem.minecraft.diamond_pickaxe":220,"stat.useItem.minecraft.ender_eye":13,"stat.useItem.minecraft.bucket":6,"stat.drop":682,"stat.pickup.minecraft.stone_button":27,"stat.killEntity.Sheep":2,"stat.drop.minecraft.redstone_block":512,"stat.useItem.minecraft.diamond_axe":32,"stat.useItem.minecraft.carpet":140,"stat.useItem.minecraft.stained_glass_pane":38,"stat.useItem.minecraft.flower_pot":2,"stat.useItem.minecraft.bedrock":4,"stat.useItem.minecraft.wooden_hoe":27,"stat.pickup.minecraft.fence":1,"stat.useItem.minecraft.mycelium":11,"stat.useItem.minecraft.stone_button":219,"stat.pickup.minecraft.diamond_ore":2,"stat.drop.minecraft.glass":1,"stat.pickup.minecraft.iron_ore":7,"stat.useItem.minecraft.redstone_lamp":12,"stat.pickup.minecraft.leaves":3,"stat.pickup.minecraft.leather":2,"stat.mineBlock.minecraft.furnace":1,"stat.useItem.minecraft.wooden_pickaxe":9,"stat.drop.minecraft.stone_button":1,"stat.drop.minecraft.water_bucket":12,"stat.useItem.minecraft.end_portal_frame":14,"stat.damageDealt":13542,"stat.killEntity.Cow":1,"stat.useItem.minecraft.crafting_table":10,"stat.killEntity.Pig":86,"stat.walkOneCm":3510668,"stat.pickup.minecraft.stick":5,"stat.useItem.minecraft.emerald_block":13,"stat.drop.minecraft.iron_block":1,"stat.useItem.minecraft.redstone_block":8,"stat.useItem.minecraft.spruce_stairs":324,"stat.pickup.minecraft.stone":134,"stat.drop.minecraft.emerald":3,"stat.drop.minecraft.diamond_leggings":3,"stat.useItem.minecraft.leaves":8,"stat.pickup.minecraft.gold_ingot":1,"stat.killEntity.Skeleton":2,"stat.useItem.minecraft.iron_block":5,"stat.killEntity.Spider":2,"stat.drop.minecraft.filled_map":2,"stat.drop.minecraft.diamond_boots":3,"stat.useItem.minecraft.hopper_minecart":13,"stat.mineBlock.minecraft.leaves":39,"stat.mineBlock.minecraft.redstone_ore":1,"stat.useItem.minecraft.map":29,"stat.mineBlock.minecraft.stone":26,"stat.useItem.minecraft.sandstone":299}